qrngtools/__init__.py
qrngtools/__main__.py
qrngtools/qrng.py
qrngtools-0.1.6.dist-info/METADATA
qrngtools-0.1.6.dist-info/WHEEL
qrngtools-0.1.6.dist-info/entry_points.txt
qrngtools-0.1.6.dist-info/top_level.txt
qrngtools-0.1.6.dist-info/RECORD
