Metadata-Version: 2.4
Name: qrngtools
Version: 0.1.6
Summary: Quantum random number generation using IBM Quantum (Qiskit)
Home-page: https://github.com/karthikeyadusi/qrngtools
Author: INVINCIBLES
Author-email: dvskartikeya@gmail.com
License: AUCE
Classifier: Development Status :: 3 - Alpha
Classifier: Intended Audience :: Developers
Classifier: Intended Audience :: Education
Classifier: Intended Audience :: Science/Research
Classifier: Topic :: Scientific/Engineering :: Physics
Classifier: Topic :: Scientific/Engineering :: Mathematics
Classifier: Topic :: Security :: Cryptography
Classifier: Programming Language :: Python :: 3
Classifier: Operating System :: OS Independent
Classifier: Environment :: Console
Classifier: Natural Language :: English
Classifier: License :: OSI Approved :: MIT License
Requires-Python: >=3.7
Requires-Dist: qiskit>=1.4.4
Requires-Dist: qiskit-aer>=0.13.0
Requires-Dist: qiskit-ibm-provider>=0.7.0
Dynamic: author
Dynamic: author-email
Dynamic: classifier
Dynamic: description
Dynamic: description-content-type
Dynamic: home-page
Dynamic: license
Dynamic: requires-dist
Dynamic: requires-python
Dynamic: summary
